TR_video_process_components/OCR_class.py
TR_video_process_components/__init__.py
TR_video_process_components/img_control.py
TR_video_process_components/img_control_wo_class.py
TR_video_process_components/live_video.py
tr_video_process_components-1.0.0.dist-info/METADATA
tr_video_process_components-1.0.0.dist-info/WHEEL
tr_video_process_components-1.0.0.dist-info/licenses/LICENSE
tr_video_process_components-1.0.0.dist-info/RECORD
